berx/__init__.py
berx/__main__.py
berx-0.1.0.dist-info/entry_points.txt
berx-0.1.0.dist-info/LICENSE
berx-0.1.0.dist-info/WHEEL
berx-0.1.0.dist-info/METADATA
berx-0.1.0.dist-info/RECORD
