Metadata-Version: 2.1
Name: berx
Version: 0.1.0
Summary: Gitea and Forgejo CLI extension tools, providing some extra functionality that is missing.
Keywords: git,gitea,codeberg,forgejo
Author-email: "Taylor C. Richberger" <taywee@gmx.com>
Maintainer-email: "Taylor C. Richberger" <taywee@gmx.com>
Requires-Python: >=3.7
Classifier: Development Status :: 1 - Planning
Classifier: Programming Language :: Python
Classifier: Topic :: Software Development :: Version Control :: Git
Classifier: Topic :: System :: Systems Administration
Classifier: Topic :: Utilities
Requires-Dist: aiohttp >=3.8.4, <4
Requires-Dist: tomlkit >=0.11.7, <0.12
Project-URL: repository, https://codeberg.org/Taywee/berx
